[{"name": "db1", "mode": 1, "owner": null, "tables": [{"name": "Persona", "inherits": null, "columns": [{"name": "Dpi", "type": "BIGINT", "size": null, "PK": true, "FK": null, "NN": true, "Default": null, "Unique": false, "Constraint": null}, {"name": "Nombre", "type": "VARCHAR", "size": 20, "PK": false, "FK": null, "NN": false, "Default": null, "Unique": false, "Constraint": null}, {"name": "fecha", "type": "DATE", "size": null, "PK": false, "FK": null, "NN": false, "Default": null, "Unique": false, "Constraint": null}, {"name": "estado", "type": "mood", "size": null, "PK": true, "FK": null, "NN": true, "Default": null, "Unique": false, "Constraint": null}, {"name": "edad", "type": "SMALLINT", "size": null, "PK": false, "FK": null, "NN": false, "Default": null, "Unique": false, "Constraint": ["edad", ["edad", 0, ">", "ID", "NUMBER"]]}]}, {"name": "Persona2", "inherits": null, "columns": [{"name": "Dpi", "type": "BIGINT", "size": null, "PK": true, "FK": null, "NN": true, "Default": null, "Unique": false, "Constraint": null}, {"name": "Nombre", "type": "VARCHAR", "size": 20, "PK": false, "FK": null, "NN": false, "Default": null, "Unique": false, "Constraint": null}, {"name": "fecha", "type": "DATE", "size": null, "PK": false, "FK": null, "NN": false, "Default": null, "Unique": false, "Constraint": null}, {"name": "estado", "type": "mood", "size": null, "PK": true, "FK": null, "NN": true, "Default": null, "Unique": false, "Constraint": null}, {"name": "Dpi2", "type": "BIGINT", "size": null, "PK": false, "FK": ["Persona", "Dpi"], "NN": false, "Default": null, "Unique": false, "Constraint": null}]}]}]